MANIFEST.in
README.md
btrfsutilpy.h
constants.c
error.c
filesystem.c
module.c
qgroup.c
setup.cfg
setup.py
subvolume.c
version.py
btrfsutil.egg-info/PKG-INFO
btrfsutil.egg-info/SOURCES.txt
btrfsutil.egg-info/dependency_links.txt
btrfsutil.egg-info/top_level.txt
tests/test_filesystem.py
tests/test_qgroup.py
tests/test_subvolume.py