Metadata-Version: 2.4
Name: btrfsutil
Version: 6.17.1
Summary: Library for managing Btrfs filesystems
Home-page: https://github.com/kdave/btrfs-progs
License: LGPLv2+
Dynamic: description
Dynamic: description-content-type
Dynamic: home-page
Dynamic: license
Dynamic: summary
